<?xml version="1.0" encoding="UTF-16" ?>
<Export>
    <FileInfo>
        <Properties>
            <tag>/File/Main/FilePath</tag>
            <type>ascii</type>
            <count>141</count>
            <value>C:\Users\ÄGARE\Documents\GitHub\Helsingerunor-1921\collection\img\Helsingerunor År 1 No. 1 masterfiler\Helsingerunor1921-1924smutsidan2.tif</value>
        </Properties>
        <Properties>
            <tag>/File/Main/FileName</tag>
            <type>ascii</type>
            <count>36</count>
            <value>Helsingerunor1921-1924smutsidan2.tif</value>
        </Properties>
        <Properties>
            <tag>/File/Main/Name</tag>
            <type>ascii</type>
            <count>32</count>
            <value>Helsingerunor1921-1924smutsidan2</value>
        </Properties>
        <Properties>
            <tag>/File/Main/FileLocation</tag>
            <type>ascii</type>
            <count>105</count>
            <value>C:\Users\ÄGARE\Documents\GitHub\Helsingerunor-1921\collection\img\Helsingerunor År 1 No. 1 masterfiler\</value>
        </Properties>
        <Properties>
            <tag>/File/Main/FileExtension</tag>
            <type>ascii</type>
            <count>3</count>
            <value>tif</value>
        </Properties>
        <Properties>
            <tag>/File/Main/FileSize</tag>
            <type>ulong</type>
            <count>1</count>
            <value>19395614</value>
        </Properties>
        <Properties>
            <tag>/File/Main/DateCreation</tag>
            <type>sysdatetime</type>
            <count>1</count>
            <value>2022-07-03 08:26:05</value>
        </Properties>
        <Properties>
            <tag>/File/Main/DateLastAccess</tag>
            <type>sysdatetime</type>
            <count>1</count>
            <value>2022-07-04 16:22:27</value>
        </Properties>
        <Properties>
            <tag>/File/Main/DateLastWrite</tag>
            <type>sysdatetime</type>
            <count>1</count>
            <value>2022-07-04 16:22:24</value>
        </Properties>
        <Properties>
            <tag>/File/Main/PixelWidth</tag>
            <type>ulong</type>
            <count>1</count>
            <value>2233</value>
        </Properties>
        <Properties>
            <tag>/File/Main/PixelHeight</tag>
            <type>ulong</type>
            <count>1</count>
            <value>2894</value>
        </Properties>
    </FileInfo>
    <ExifInfo>
        <Properties>
            <tag>/Exif/Image/NewSubfileType</tag>
            <type>ushort</type>
            <count>1</count>
            <value>2</value>
        </Properties>
        <Properties>
            <tag>/Exif/Image/ImageWidth</tag>
            <type>ushort</type>
            <count>1</count>
            <value>2233</value>
        </Properties>
        <Properties>
            <tag>/Exif/Image/ImageLength</tag>
            <type>ushort</type>
            <count>1</count>
            <value>2894</value>
        </Properties>
        <Properties>
            <tag>/Exif/Image/BitsPerSample</tag>
            <type>ushort</type>
            <count>3</count>
            <value>8 8 8</value>
        </Properties>
        <Properties>
            <tag>/Exif/Image/Compression</tag>
            <type>ushort</type>
            <count>1</count>
            <value>1</value>
        </Properties>
        <Properties>
            <tag>/Exif/Image/PhotometricInterpretation</tag>
            <type>ushort</type>
            <count>1</count>
            <value>2</value>
        </Properties>
        <Properties>
            <tag>/Exif/Image/FillOrder</tag>
            <type>ushort</type>
            <count>1</count>
            <value>1</value>
        </Properties>
        <Properties>
            <tag>/Exif/Image/Model</tag>
            <type>ascii</type>
            <count>20</count>
            <value>Zeta comfort HX-4899</value>
        </Properties>
        <Properties>
            <tag>/Exif/Image/Orientation</tag>
            <type>ushort</type>
            <count>1</count>
            <value>1</value>
        </Properties>
        <Properties>
            <tag>/Exif/Image/SamplesPerPixel</tag>
            <type>ushort</type>
            <count>1</count>
            <value>3</value>
        </Properties>
        <Properties>
            <tag>/Exif/Image/XResolution</tag>
            <type>urational</type>
            <count>1</count>
            <value>300/1</value>
        </Properties>
        <Properties>
            <tag>/Exif/Image/YResolution</tag>
            <type>urational</type>
            <count>1</count>
            <value>300/1</value>
        </Properties>
        <Properties>
            <tag>/Exif/Image/PlanarConfiguration</tag>
            <type>ushort</type>
            <count>1</count>
            <value>1</value>
        </Properties>
        <Properties>
            <tag>/Exif/Image/ResolutionUnit</tag>
            <type>ushort</type>
            <count>1</count>
            <value>2</value>
        </Properties>
        <Properties>
            <tag>/Exif/Image/PageNumber</tag>
            <type>ushort</type>
            <count>2</count>
            <value>0 1</value>
        </Properties>
        <Properties>
            <tag>/Exif/Image/Software</tag>
            <type>ascii</type>
            <count>9</count>
            <value>ImageGear</value>
        </Properties>
        <Properties>
            <tag>/Exif/Image/DateTime</tag>
            <type>ascii</type>
            <count>19</count>
            <value>2007-11-06 06:21:21</value>
        </Properties>
        <Properties>
            <tag>/Exif/Image/Artist</tag>
            <type>ascii</type>
            <count>14</count>
            <value>Edit Henriksen</value>
        </Properties>
        <Properties>
            <tag>/Exif/Image/XMLPacket</tag>
            <type>byte</type>
            <count>5944</count>
            <value>60 63 120 112 97 99 107 101 116 32 98 101 103 105 110 61  ...</value>
        </Properties>
        <Properties>
            <tag>/Exif/Image/IPTC_NAA</tag>
            <type>undefined</type>
            <count>21</count>
            <value>1C  1 5A  0  3 1B 25 47 1C  2  0  0  2  0  4 1C  2 37  0  8 32</value>
        </Properties>
        <Properties>
            <tag>/Exif/Photo/ExifVersion</tag>
            <type>undefined</type>
            <count>4</count>
            <value>0231</value>
        </Properties>
        <Properties>
            <tag>/Exif/Photo/DateTimeOriginal</tag>
            <type>ascii</type>
            <count>19</count>
            <value>2022-03-16</value>
        </Properties>
        <Properties>
            <tag>/Exif/Photo/OffsetTimeOriginal</tag>
            <type>ascii</type>
            <count>6</count>
            <value>+02:00</value>
        </Properties>
        <Properties>
            <tag>/Exif/Thumbnail/Compression</tag>
            <type>ushort</type>
            <count>1</count>
            <value>6</value>
        </Properties>
    </ExifInfo>
    <IptcInfo>
        <Properties>
            <tag>/Iptc/Envelope/CodedCharacterSet</tag>
            <type>undefined</type>
            <count>3</count>
            <value>1B 25 47</value>
        </Properties>
        <Properties>
            <tag>/Iptc/Application/RecordVersion</tag>
            <type>ushort</type>
            <count>1</count>
            <value>4</value>
        </Properties>
        <Properties>
            <tag>/Iptc/Application/DateCreated</tag>
            <type>iptcdate</type>
            <count>1</count>
            <value>2022-03-16</value>
        </Properties>
        <Properties>
            <tag>/Iptc/Application/TimeCreated</tag>
            <type>iptctime</type>
            <count>1</count>
            <value>00:00:00 + 02:00</value>
        </Properties>
        <Properties>
            <tag>/Iptc/Application/Byline</tag>
            <type>ascii</type>
            <count>14</count>
            <value>Edit Henriksen</value>
        </Properties>
        <Properties>
            <tag>/Iptc/Application/Source</tag>
            <type>ascii</type>
            <count>13</count>
            <value>Helsingerunor</value>
        </Properties>
    </IptcInfo>
    <XmpInfo>
        <Properties>
            <tag>/Xmp/ExifStandard/ColorSpace</tag>
            <type>xmptext</type>
            <count>5</count>
            <value>65535</value>
        </Properties>
        <Properties>
            <tag>/Xmp/XMPBasic/CreatorTool</tag>
            <type>xmptext</type>
            <count>9</count>
            <value>ImageGear</value>
        </Properties>
        <Properties>
            <tag>/Xmp/XMPBasic/ModifyDate</tag>
            <type>xmptext</type>
            <count>19</count>
            <value>2007-11-06T06:21:21</value>
        </Properties>
        <Properties>
            <tag>/Xmp/XMPBasic/MetadataDate</tag>
            <type>xmptext</type>
            <count>25</count>
            <value>2022-07-04T16:10:03+02:00</value>
        </Properties>
        <Properties>
            <tag>/Xmp/ExifTiff/Orientation</tag>
            <type>xmptext</type>
            <count>1</count>
            <value>1</value>
        </Properties>
        <Properties>
            <tag>/Xmp/XMPMediaManagement/DocumentID</tag>
            <type>xmptext</type>
            <count>32</count>
            <value>4FBB98A469340B4BB44FD4167AE71105</value>
        </Properties>
        <Properties>
            <tag>/Xmp/XMPMediaManagement/OriginalDocumentID</tag>
            <type>xmptext</type>
            <count>32</count>
            <value>4FBB98A469340B4BB44FD4167AE71105</value>
        </Properties>
        <Properties>
            <tag>/Xmp/XMPMediaManagement/InstanceID</tag>
            <type>xmptext</type>
            <count>44</count>
            <value>xmp.iid:e051123f-0cd2-e94e-a5e7-f6f5b6814e36</value>
        </Properties>
        <Properties>
            <tag>/Xmp/XMPMediaManagement/History</tag>
            <type>xmptext</type>
            <count>0</count>
            <value></value>
        </Properties>
        <Properties>
            <tag>/Xmp/AdobePhotoshop/Source</tag>
            <type>xmptext</type>
            <count>13</count>
            <value>Helsingerunor</value>
        </Properties>
        <Properties>
            <tag>/Xmp/AdobePhotoshop/DateCreated</tag>
            <type>xmptext</type>
            <count>25</count>
            <value>2022-03-16T00:00:00+02:00</value>
        </Properties>
        <Properties>
            <tag>/Xmp/AdobePhotoshop/AuthorsPosition</tag>
            <type>xmptext</type>
            <count>32</count>
            <value>FAAC6E6A16D46933F5A4C22A0DB554E0</value>
        </Properties>
        <Properties>
            <tag>/Xmp/XMPRightsManagement/Marked</tag>
            <type>xmptext</type>
            <count>4</count>
            <value>True</value>
        </Properties>
        <Properties>
            <tag>/Xmp/Iptc4XmpExtension/AddlModelInfo</tag>
            <type>xmptext</type>
            <count>9</count>
            <value>http://cv.iptc.org/newscodes/digitalsourcetype/print; ; Djurgårdsvägen 6-16; Stockholm; Sverige; ; Ovanåker; ; Edsbyn </value>
        </Properties>
        <Properties>
            <tag>/Xmp/Iptc4XmpExtension/OrganisationInImageName</tag>
            <type>xmparray</type>
            <count>9</count>
            <value>L. E. Norins Herrskrädderi och Manufakturaffär; Hedberg &amp; C:o Snickerifabrik; Gylén &amp; C:o Slakteri och Chrkuteriaffär; Edsbyns Ullspinneri; Edmark &amp; C:o Järnvaror; Byggnadsmaterial; Möbler; Leo Carlsson Glas-; Porslin- och Bosättningsaffär</value>
        </Properties>
        <Properties>
            <tag>/Xmp/DublinCore/Format</tag>
            <type>xmptext</type>
            <count>10</count>
            <value>image/tiff</value>
        </Properties>
        <Properties>
            <tag>/Xmp/DublinCore/Creator</tag>
            <type>xmparray</type>
            <count>1</count>
            <value>Edit Henriksen</value>
        </Properties>
        <Properties>
            <tag>/Xmp/DublinCore/Date</tag>
            <type>xmparray</type>
            <count>1</count>
            <value>2022-03-16</value>
        </Properties>
        <Properties>
            <tag>/Xmp/DublinCore/Language</tag>
            <type>xmparray</type>
            <count>1</count>
            <value>Svenska</value>
        </Properties>
        <Properties>
            <tag>/Xmp/DublinCore/Relation</tag>
            <type>xmparray</type>
            <count>2</count>
            <value>https://libris.kb.se/sx438g8z5bqx8hh#it; Helsingerunor 1921 årgång 1 volym 1 </value>
        </Properties>
        <Properties>
            <tag>/Xmp/IptcStandard/Creator&apos;sContactInfo</tag>
            <type>xmptext</type>
            <count>0</count>
            <value></value>
        </Properties>
        <Properties>
            <tag>/Xmp/IptcStandard/ContactInfoCity</tag>
            <type>xmptext</type>
            <count>5</count>
            <value>Djurgårdsvägen 6-16; Stockholm; 115 93; Sverige; Stockholm</value>
        </Properties>
    </XmpInfo>
</Export>
